AUTHORS.rst
CONTRIBUTING.rst
HISTORY.rst
LICENSE
MANIFEST.in
README.rst
requirements-test.txt
requirements.txt
setup.cfg
setup.py
docs/Makefile
docs/authors.rst
docs/conf.py
docs/contributing.rst
docs/history.rst
docs/index.rst
docs/installation.rst
docs/make.bat
docs/readme.rst
docs/usage.rst
precs/__init__.py
precs/precs.py
precs.egg-info/PKG-INFO
precs.egg-info/SOURCES.txt
precs.egg-info/dependency_links.txt
precs.egg-info/entry_points.txt
precs.egg-info/not-zip-safe
precs.egg-info/requires.txt
precs.egg-info/top_level.txt
precs/processors/__init__.py
precs/processors/kv.py
tests/__init__.py
tests/kv_testdata.py
tests/test_fromkv.py