Metadata-Version: 1.1
Name: precs
Version: 0.1.0a3
Summary: Python implementation of record stream processing utilities.
Home-page: https://github.com/umerazad/precs
Author: Muhammad Umer Azad
Author-email: umer.azad@gmail.com
License: MIT
Keywords: precs
Platform: UNKNOWN
Classifier: Development Status :: 2 - Pre-Alpha
Classifier: Intended Audience :: Developers
Classifier: Natural Language :: English
Classifier: Programming Language :: Python :: 2.7
